[
  {
    "code": 4981,
    "district_code": 523,
    "name": "Achanta"
  },
  {
    "code": 5112,
    "district_code": 750,
    "name": "Addanki"
  },
  {
    "code": 4887,
    "district_code": 745,
    "name": "Addateegala"
  },
  {
    "code": 5271,
    "district_code": 511,
    "name": "Adoni"
  },
  {
    "code": 5354,
    "district_code": 754,
    "name": "Agali"
  },
  {
    "code": 5005,
    "district_code": 748,
    "name": "Agiripalli"
  },
  {
    "code": 4933,
    "district_code": 747,
    "name": "Ainavilli"
  },
  {
    "code": 4975,
    "district_code": 523,
    "name": "Akividu"
  },
  {
    "code": 4925,
    "district_code": 747,
    "name": "Alamuru"
  },
  {
    "code": 5298,
    "district_code": 755,
    "name": "Allagadda"
  },
  {
    "code": 4940,
    "district_code": 747,
    "name": "Allavaram"
  },
  {
    "code": 5167,
    "district_code": 515,
    "name": "Allur"
  },
  {
    "code": 5274,
    "district_code": 511,
    "name": "Alur"
  },
  {
    "code": 5361,
    "district_code": 754,
    "name": "Amadagur"
  },
  {
    "code": 4798,
    "district_code": 519,
    "name": "Amadalavalasa"
  },
  {
    "code": 4941,
    "district_code": 747,
    "name": "Amalapuram"
  },
  {
    "code": 5351,
    "district_code": 754,
    "name": "Amarapuram"
  },
  {
    "code": 5052,
    "district_code": 751,
    "name": "Amaravathi"
  },
  {
    "code": 5086,
    "district_code": 750,
    "name": "Amarthalur"
  },
  {
    "code": 4935,
    "district_code": 747,
    "name": "Ambajipeta"
  },
  {
    "code": 4871,
    "district_code": 744,
    "name": "Anakapalli"
  },
  {
    "code": 4863,
    "district_code": 520,
    "name": "Anandapuram"
  },
  {
    "code": 5330,
    "district_code": 502,
    "name": "Anantapur Rural"
  },
  {
    "code": 7426,
    "district_code": 502,
    "name": "Anantapur Urban"
  },
  {
    "code": 4845,
    "district_code": 745,
    "name": "Ananthagiri"
  },
  {
    "code": 5173,
    "district_code": 515,
    "name": "Ananthasagaram"
  },
  {
    "code": 4917,
    "district_code": 505,
    "name": "Anaparthi"
  },
  {
    "code": 5165,
    "district_code": 515,
    "name": "Anumasamudrampeta"
  },
  {
    "code": 4844,
    "district_code": 745,
    "name": "Araku Valley"
  },
  {
    "code": 5116,
    "district_code": 517,
    "name": "Ardhaveedu"
  },
  {
    "code": 5275,
    "district_code": 511,
    "name": "Aspari"
  },
  {
    "code": 5050,
    "district_code": 751,
    "name": "Atchampet"
  },
  {
    "code": 4878,
    "district_code": 744,
    "name": "Atchuthapuram"
  },
  {
    "code": 4998,
    "district_code": 749,
    "name": "Atlapragada Konduru"
  },
  {
    "code": 5227,
    "district_code": 504,
    "name": "Atlur"
  },
  {
    "code": 5322,
    "district_code": 502,
    "name": "Atmakur"
  },
  {
    "code": 5164,
    "district_code": 515,
    "name": "Atmakur"
  },
  {
    "code": 5265,
    "district_code": 755,
    "name": "Atmakur"
  },
  {
    "code": 4919,
    "district_code": 747,
    "name": "Atreyapuram"
  },
  {
    "code": 4973,
    "district_code": 523,
    "name": "Attili"
  },
  {
    "code": 5037,
    "district_code": 510,
    "name": "Avanigadda"
  },
  {
    "code": 4820,
    "district_code": 521,
    "name": "Badangi"
  },
  {
    "code": 5210,
    "district_code": 504,
    "name": "Badvel"
  },
  {
    "code": 5423,
    "district_code": 503,
    "name": "Baireddipalle"
  },
  {
    "code": 5188,
    "district_code": 752,
    "name": "Balayapalli"
  },
  {
    "code": 4815,
    "district_code": 743,
    "name": "Balijipeta"
  },
  {
    "code": 5105,
    "district_code": 750,
    "name": "Ballikurava"
  },
  {
    "code": 5288,
    "district_code": 755,
    "name": "Banaganapalli"
  },
  {
    "code": 5283,
    "district_code": 755,
    "name": "Bandi Atmakur"
  },
  {
    "code": 5429,
    "district_code": 503,
    "name": "Bangarupalem"
  },
  {
    "code": 5019,
    "district_code": 510,
    "name": "Bantumilli"
  },
  {
    "code": 5093,
    "district_code": 750,
    "name": "Bapatla"
  },
  {
    "code": 5004,
    "district_code": 510,
    "name": "Bapulapadu"
  },
  {
    "code": 5337,
    "district_code": 754,
    "name": "Bathalapalli"
  },
  {
    "code": 5391,
    "district_code": 753,
    "name": "Beerongi Kothakota"
  },
  {
    "code": 5049,
    "district_code": 751,
    "name": "Bellamkonda"
  },
  {
    "code": 5318,
    "district_code": 502,
    "name": "Beluguppa"
  },
  {
    "code": 5131,
    "district_code": 517,
    "name": "Bestavaripeta"
  },
  {
    "code": 5279,
    "district_code": 755,
    "name": "Bethamcherla"
  },
  {
    "code": 4771,
    "district_code": 743,
    "name": "Bhamini"
  },
  {
    "code": 5089,
    "district_code": 750,
    "name": "Bhattiprolu"
  },
  {
    "code": 4963,
    "district_code": 748,
    "name": "Bheemadole"
  },
  {
    "code": 4865,
    "district_code": 520,
    "name": "Bheemunipatnam"
  },
  {
    "code": 4984,
    "district_code": 523,
    "name": "Bhimavaram"
  },
  {
    "code": 4840,
    "district_code": 521,
    "name": "Bhogapuram"
  },
  {
    "code": 4916,
    "district_code": 505,
    "name": "Biccavolu"
  },
  {
    "code": 5209,
    "district_code": 504,
    "name": "B.Kodur"
  },
  {
    "code": 4816,
    "district_code": 521,
    "name": "Bobbili"
  },
  {
    "code": 5159,
    "district_code": 515,
    "name": "Bogole"
  },
  {
    "code": 5061,
    "district_code": 751,
    "name": "Bollapalli"
  },
  {
    "code": 5307,
    "district_code": 502,
    "name": "Bommanahal"
  },
  {
    "code": 4829,
    "district_code": 521,
    "name": "Bondapalli"
  },
  {
    "code": 5205,
    "district_code": 504,
    "name": "Brahmamgarimattam"
  },
  {
    "code": 5320,
    "district_code": 502,
    "name": "Brahmasamudram"
  },
  {
    "code": 5380,
    "district_code": 752,
    "name": "Buchinaidu Kandriga"
  },
  {
    "code": 5170,
    "district_code": 515,
    "name": "Buchireddipalem"
  },
  {
    "code": 5345,
    "district_code": 754,
    "name": "Bukkapatnam"
  },
  {
    "code": 5329,
    "district_code": 502,
    "name": "Bukkaraya Samudram"
  },
  {
    "code": 4794,
    "district_code": 519,
    "name": "Burja"
  },
  {
    "code": 4873,
    "district_code": 744,
    "name": "Butchayyapeta"
  },
  {
    "code": 4948,
    "district_code": 748,
    "name": "Buttayagudem"
  },
  {
    "code": 5256,
    "district_code": 511,
    "name": "C.Belagal"
  },
  {
    "code": 5303,
    "district_code": 755,
    "name": "Chagalamarri"
  },
  {
    "code": 4959,
    "district_code": 505,
    "name": "Chagallu"
  },
  {
    "code": 5234,
    "district_code": 504,
    "name": "Chakrayapet"
  },
  {
    "code": 5035,
    "district_code": 510,
    "name": "Challapalli"
  },
  {
    "code": 5008,
    "district_code": 749,
    "name": "Chandarlapadu"
  },
  {
    "code": 5384,
    "district_code": 752,
    "name": "Chandragiri"
  },
  {
    "code": 5145,
    "district_code": 517,
    "name": "Chandra Sekhara Puram"
  },
  {
    "code": 5213,
    "district_code": 504,
    "name": "Chapad"
  },
  {
    "code": 5001,
    "district_code": 748,
    "name": "Chatrai"
  },
  {
    "code": 5079,
    "district_code": 506,
    "name": "Chebrolu"
  },
  {
    "code": 4858,
    "district_code": 744,
    "name": "Cheedikada"
  },
  {
    "code": 4827,
    "district_code": 521,
    "name": "Cheepurupalli"
  },
  {
    "code": 5172,
    "district_code": 515,
    "name": "Chejerla"
  },
  {
    "code": 5347,
    "district_code": 754,
    "name": "Chennekothapalli"
  },
  {
    "code": 5226,
    "district_code": 504,
    "name": "Chennur"
  },
  {
    "code": 5090,
    "district_code": 750,
    "name": "Cherukupalli"
  },
  {
    "code": 5070,
    "district_code": 751,
    "name": "Chilakaluripet H/ O.Purushotha Patnam"
  },
  {
    "code": 5366,
    "district_code": 754,
    "name": "Chilamathur"
  },
  {
    "code": 5190,
    "district_code": 752,
    "name": "Chillakur"
  },
  {
    "code": 5128,
    "district_code": 517,
    "name": "Chimakurthy"
  },
  {
    "code": 5125,
    "district_code": 750,
    "name": "Chinaganjam"
  },
  {
    "code": 5385,
    "district_code": 752,
    "name": "Chinnagottigallu"
  },
  {
    "code": 5236,
    "district_code": 753,
    "name": "Chinnamandem"
  },
  {
    "code": 4944,
    "district_code": 748,
    "name": "Chintalapudi"
  },
  {
    "code": 5231,
    "district_code": 504,
    "name": "Chinthakommadinne"
  },
  {
    "code": 4849,
    "district_code": 745,
    "name": "Chinthapalli"
  },
  {
    "code": 4732,
    "district_code": 745,
    "name": "Chinturu"
  },
  {
    "code": 5291,
    "district_code": 511,
    "name": "Chippagiri"
  },
  {
    "code": 5123,
    "district_code": 750,
    "name": "Chirala"
  },
  {
    "code": 5193,
    "district_code": 752,
    "name": "Chittamur"
  },
  {
    "code": 5421,
    "district_code": 503,
    "name": "Chittoor Rural"
  },
  {
    "code": 7427,
    "district_code": 503,
    "name": "Chittoor Urban"
  },
  {
    "code": 5245,
    "district_code": 753,
    "name": "Chitvel"
  },
  {
    "code": 4872,
    "district_code": 744,
    "name": "Chodavaram"
  },
  {
    "code": 5413,
    "district_code": 503,
    "name": "Chowdepalle"
  },
  {
    "code": 5117,
    "district_code": 517,
    "name": "Cumbum"
  },
  {
    "code": 5045,
    "district_code": 751,
    "name": "Dachepalli"
  },
  {
    "code": 5166,
    "district_code": 515,
    "name": "Dagadarthi"
  },
  {
    "code": 5186,
    "district_code": 752,
    "name": "Dakkili"
  },
  {
    "code": 5114,
    "district_code": 517,
    "name": "Darsi"
  },
  {
    "code": 4823,
    "district_code": 521,
    "name": "Dattirajeru"
  },
  {
    "code": 4967,
    "district_code": 748,
    "name": "Denduluru"
  },
  {
    "code": 4839,
    "district_code": 521,
    "name": "Denkada"
  },
  {
    "code": 5276,
    "district_code": 511,
    "name": "Devanakonda"
  },
  {
    "code": 4957,
    "district_code": 505,
    "name": "Devarapalle"
  },
  {
    "code": 4859,
    "district_code": 744,
    "name": "Devarapalli"
  },
  {
    "code": 4885,
    "district_code": 745,
    "name": "Devipatnam"
  },
  {
    "code": 5336,
    "district_code": 754,
    "name": "Dharmavaram"
  },
  {
    "code": 5304,
    "district_code": 502,
    "name": "D.Hirehal"
  },
  {
    "code": 5289,
    "district_code": 755,
    "name": "Dhone"
  },
  {
    "code": 5102,
    "district_code": 517,
    "name": "Donakonda"
  },
  {
    "code": 5196,
    "district_code": 752,
    "name": "Doravarisatram"
  },
  {
    "code": 5100,
    "district_code": 517,
    "name": "Dornala"
  },
  {
    "code": 5299,
    "district_code": 755,
    "name": "Dornipadu"
  },
  {
    "code": 5076,
    "district_code": 506,
    "name": "Duggirala"
  },
  {
    "code": 4843,
    "district_code": 745,
    "name": "Dumbriguda"
  },
  {
    "code": 5042,
    "district_code": 751,
    "name": "Durgi"
  },
  {
    "code": 5162,
    "district_code": 515,
    "name": "Duttalur"
  },
  {
    "code": 5203,
    "district_code": 504,
    "name": "Duvvur"
  },
  {
    "code": 4955,
    "district_code": 748,
    "name": "Dwarakatirumala"
  },
  {
    "code": 5071,
    "district_code": 751,
    "name": "Edlapadu"
  },
  {
    "code": 4966,
    "district_code": 748,
    "name": "Eluru Rural"
  },
  {
    "code": 7428,
    "district_code": 748,
    "name": "Eluru Urban"
  },
  {
    "code": 4806,
    "district_code": 519,
    "name": "Etcherla"
  },
  {
    "code": 5006,
    "district_code": 749,
    "name": "Gaddamanugu Konduru"
  },
  {
    "code": 5281,
    "district_code": 755,
    "name": "Gadivemula"
  },
  {
    "code": 4825,
    "district_code": 521,
    "name": "Gajapathinagaram"
  },
  {
    "code": 4869,
    "district_code": 520,
    "name": "Gajuwaka"
  },
  {
    "code": 5235,
    "district_code": 753,
    "name": "Galiveedu"
  },
  {
    "code": 4996,
    "district_code": 749,
    "name": "Gampalagudem"
  },
  {
    "code": 4974,
    "district_code": 523,
    "name": "Ganapavaram"
  },
  {
    "code": 4904,
    "district_code": 746,
    "name": "Gandepalli"
  },
  {
    "code": 5342,
    "district_code": 754,
    "name": "Gandlapenta"
  },
  {
    "code": 5420,
    "district_code": 503,
    "name": "Gangadhara Nellore"
  },
  {
    "code": 5417,
    "district_code": 503,
    "name": "Gangavaram"
  },
  {
    "code": 4894,
    "district_code": 745,
    "name": "Gangavaram"
  },
  {
    "code": 4797,
    "district_code": 519,
    "name": "Ganguvarisigadam"
  },
  {
    "code": 5012,
    "district_code": 510,
    "name": "Gannavaram"
  },
  {
    "code": 4830,
    "district_code": 521,
    "name": "Gantyada"
  },
  {
    "code": 4801,
    "district_code": 519,
    "name": "Gara"
  },
  {
    "code": 4826,
    "district_code": 521,
    "name": "Garividi"
  },
  {
    "code": 5324,
    "district_code": 502,
    "name": "Garladinne"
  },
  {
    "code": 4811,
    "district_code": 743,
    "name": "Garugubilli"
  },
  {
    "code": 5033,
    "district_code": 510,
    "name": "Ghantasala"
  },
  {
    "code": 5133,
    "district_code": 517,
    "name": "Giddalur"
  },
  {
    "code": 4848,
    "district_code": 745,
    "name": "G.Madugula"
  },
  {
    "code": 4897,
    "district_code": 505,
    "name": "Gokavaram"
  },
  {
    "code": 4902,
    "district_code": 746,
    "name": "Gollaprolu"
  },
  {
    "code": 4853,
    "district_code": 744,
    "name": "Golugonda"
  },
  {
    "code": 5270,
    "district_code": 511,
    "name": "Gonegandla"
  },
  {
    "code": 5310,
    "district_code": 502,
    "name": "Gooty"
  },
  {
    "code": 6838,
    "district_code": 520,
    "name": "Gopalapatnam"
  },
  {
    "code": 4951,
    "district_code": 505,
    "name": "Gopalapuram"
  },
  {
    "code": 5211,
    "district_code": 504,
    "name": "Gopavaram"
  },
  {
    "code": 5362,
    "district_code": 754,
    "name": "Gorantla"
  },
  {
    "code": 5287,
    "district_code": 755,
    "name": "Gospadu"
  },
  {
    "code": 4850,
    "district_code": 745,
    "name": "Gudem Kotha Veedhi"
  },
  {
    "code": 5352,
    "district_code": 754,
    "name": "Gudibanda"
  },
  {
    "code": 5431,
    "district_code": 503,
    "name": "Gudipala"
  },
  {
    "code": 5021,
    "district_code": 510,
    "name": "Gudivada"
  },
  {
    "code": 5029,
    "district_code": 510,
    "name": "Gudlavalleru"
  },
  {
    "code": 5151,
    "district_code": 515,
    "name": "Gudluru"
  },
  {
    "code": 5426,
    "district_code": 503,
    "name": "Gudupalle"
  },
  {
    "code": 5257,
    "district_code": 511,
    "name": "Gudur"
  },
  {
    "code": 5184,
    "district_code": 752,
    "name": "Gudur"
  },
  {
    "code": 5031,
    "district_code": 510,
    "name": "Guduru"
  },
  {
    "code": 5319,
    "district_code": 502,
    "name": "Gummagatta"
  },
  {
    "code": 4808,
    "district_code": 743,
    "name": "Gummalakshmipuram"
  },
  {
    "code": 5309,
    "district_code": 502,
    "name": "Guntakal"
  },
  {
    "code": 6833,
    "district_code": 506,
    "name": "Guntur East"
  },
  {
    "code": 5074,
    "district_code": 506,
    "name": "Guntur West"
  },
  {
    "code": 5044,
    "district_code": 751,
    "name": "Gurajala"
  },
  {
    "code": 4828,
    "district_code": 521,
    "name": "Gurla"
  },
  {
    "code": 5370,
    "district_code": 753,
    "name": "Gurramkonda"
  },
  {
    "code": 5273,
    "district_code": 511,
    "name": "Halaharvi"
  },
  {
    "code": 5130,
    "district_code": 517,
    "name": "Hanumanthuni Padu"
  },
  {
    "code": 5364,
    "district_code": 754,
    "name": "Hindupur"
  },
  {
    "code": 4783,
    "district_code": 519,
    "name": "Hiramandalam"
  },
  {
    "code": 5272,
    "district_code": 511,
    "name": "Holagunda"
  },
  {
    "code": 4846,
    "district_code": 745,
    "name": "Hukumpeta"
  },
  {
    "code": 5009,
    "district_code": 749,
    "name": "Ibrahimpatnam"
  },
  {
    "code": 4778,
    "district_code": 519,
    "name": "Ichchapuram"
  },
  {
    "code": 5179,
    "district_code": 515,
    "name": "Indukurpet"
  },
  {
    "code": 5110,
    "district_code": 750,
    "name": "Inkollu"
  },
  {
    "code": 4931,
    "district_code": 747,
    "name": "I. Polavaram"
  },
  {
    "code": 5065,
    "district_code": 751,
    "name": "Ipuru"
  },
  {
    "code": 4979,
    "district_code": 523,
    "name": "Iragavaram"
  },
  {
    "code": 5411,
    "district_code": 503,
    "name": "Irala"
  },
  {
    "code": 4991,
    "district_code": 749,
    "name": "Jaggaiahpeta"
  },
  {
    "code": 4898,
    "district_code": 746,
    "name": "Jaggampeta"
  },
  {
    "code": 5157,
    "district_code": 515,
    "name": "Jaladanki"
  },
  {
    "code": 4792,
    "district_code": 519,
    "name": "Jalumuru"
  },
  {
    "code": 4835,
    "district_code": 521,
    "name": "Jami"
  },
  {
    "code": 5215,
    "district_code": 504,
    "name": "Jammalamadugu"
  },
  {
    "code": 4953,
    "district_code": 748,
    "name": "Jangareddigudem"
  },
  {
    "code": 4947,
    "district_code": 748,
    "name": "Jeelugu Milli"
  },
  {
    "code": 4810,
    "district_code": 743,
    "name": "Jiyyammavalasa"
  },
  {
    "code": 5111,
    "district_code": 750,
    "name": "J.Pangulur"
  },
  {
    "code": 5262,
    "district_code": 755,
    "name": "Jupadu Bunglow"
  },
  {
    "code": 5230,
    "district_code": 504,
    "name": "Kadapa"
  },
  {
    "code": 4918,
    "district_code": 505,
    "name": "Kadiam"
  },
  {
    "code": 5343,
    "district_code": 754,
    "name": "Kadiri"
  },
  {
    "code": 5016,
    "district_code": 748,
    "name": "Kaikaluru"
  },
  {
    "code": 4923,
    "district_code": 746,
    "name": "Kajuluru"
  },
  {
    "code": 4913,
    "district_code": 746,
    "name": "Kakinada (Rural)"
  },
  {
    "code": 4914,
    "district_code": 746,
    "name": "Kakinada (Urban)"
  },
  {
    "code": 5083,
    "district_code": 506,
    "name": "Kakumanu"
  },
  {
    "code": 5371,
    "district_code": 753,
    "name": "Kalakada"
  },
  {
    "code": 5207,
    "district_code": 504,
    "name": "Kalasapadu"
  },
  {
    "code": 5017,
    "district_code": 748,
    "name": "Kalidindi"
  },
  {
    "code": 5160,
    "district_code": 515,
    "name": "Kaligiri"
  },
  {
    "code": 5387,
    "district_code": 753,
    "name": "Kalikiri"
  },
  {
    "code": 4985,
    "district_code": 523,
    "name": "Kalla"
  },
  {
    "code": 5258,
    "district_code": 511,
    "name": "Kallur"
  },
  {
    "code": 5174,
    "district_code": 515,
    "name": "Kaluvoya"
  },
  {
    "code": 5321,
    "district_code": 502,
    "name": "Kalyanadurg"
  },
  {
    "code": 5224,
    "district_code": 504,
    "name": "Kamalapuram"
  },
  {
    "code": 4954,
    "district_code": 748,
    "name": "Kamavarapukota"
  },
  {
    "code": 5334,
    "district_code": 502,
    "name": "Kambadur"
  },
  {
    "code": 5372,
    "district_code": 753,
    "name": "Kambhamvaripalle"
  },
  {
    "code": 5335,
    "district_code": 754,
    "name": "Kanaganipalli"
  },
  {
    "code": 5007,
    "district_code": 749,
    "name": "Kanchikacherla"
  },
  {
    "code": 4777,
    "district_code": 519,
    "name": "Kanchili"
  },
  {
    "code": 5148,
    "district_code": 515,
    "name": "Kandukuru"
  },
  {
    "code": 5306,
    "district_code": 502,
    "name": "Kanekal"
  },
  {
    "code": 5136,
    "district_code": 517,
    "name": "Kanigiri"
  },
  {
    "code": 5023,
    "district_code": 510,
    "name": "Kankipadu"
  },
  {
    "code": 4928,
    "district_code": 747,
    "name": "Kapileswarapuram"
  },
  {
    "code": 5109,
    "district_code": 750,
    "name": "Karamchedu"
  },
  {
    "code": 4922,
    "district_code": 746,
    "name": "Karapa"
  },
  {
    "code": 5046,
    "district_code": 751,
    "name": "Karempudi"
  },
  {
    "code": 5092,
    "district_code": 750,
    "name": "Karlapalem"
  },
  {
    "code": 5408,
    "district_code": 503,
    "name": "Karvetinagar"
  },
  {
    "code": 4876,
    "district_code": 744,
    "name": "Kasimkota"
  },
  {
    "code": 4943,
    "district_code": 747,
    "name": "Katrenikona"
  },
  {
    "code": 5158,
    "district_code": 515,
    "name": "Kavali"
  },
  {
    "code": 4779,
    "district_code": 519,
    "name": "Kaviti"
  },
  {
    "code": 4929,
    "district_code": 747,
    "name": "K Gangavaram"
  },
  {
    "code": 5212,
    "district_code": 504,
    "name": "Khajipeta"
  },
  {
    "code": 4899,
    "district_code": 746,
    "name": "Kirlampudi"
  },
  {
    "code": 4860,
    "district_code": 744,
    "name": "K.Kotapadu"
  },
  {
    "code": 5169,
    "district_code": 515,
    "name": "Kodavalur"
  },
  {
    "code": 5269,
    "district_code": 511,
    "name": "Kodumur"
  },
  {
    "code": 5249,
    "district_code": 753,
    "name": "Kodur"
  },
  {
    "code": 5039,
    "district_code": 510,
    "name": "Koduru"
  },
  {
    "code": 5296,
    "district_code": 755,
    "name": "Koilakuntla"
  },
  {
    "code": 5301,
    "district_code": 755,
    "name": "Kolimigundla"
  },
  {
    "code": 5077,
    "district_code": 506,
    "name": "Kollipara"
  },
  {
    "code": 5088,
    "district_code": 750,
    "name": "Kolluru"
  },
  {
    "code": 4807,
    "district_code": 743,
    "name": "Komarada"
  },
  {
    "code": 5134,
    "district_code": 517,
    "name": "Komarolu"
  },
  {
    "code": 5119,
    "district_code": 517,
    "name": "Konakanamitla"
  },
  {
    "code": 5137,
    "district_code": 517,
    "name": "Kondapi"
  },
  {
    "code": 5156,
    "district_code": 515,
    "name": "Kondapuram"
  },
  {
    "code": 5199,
    "district_code": 504,
    "name": "Kondapuram"
  },
  {
    "code": 5122,
    "district_code": 750,
    "name": "Korisapadu"
  },
  {
    "code": 4905,
    "district_code": 505,
    "name": "Korukonda"
  },
  {
    "code": 5251,
    "district_code": 511,
    "name": "Kosigi"
  },
  {
    "code": 5191,
    "district_code": 752,
    "name": "Kota"
  },
  {
    "code": 4791,
    "district_code": 519,
    "name": "Kotabommali"
  },
  {
    "code": 4889,
    "district_code": 746,
    "name": "Kotananduru"
  },
  {
    "code": 4874,
    "district_code": 744,
    "name": "Kotauratla"
  },
  {
    "code": 5346,
    "district_code": 754,
    "name": "Kothacheruvu"
  },
  {
    "code": 5263,
    "district_code": 755,
    "name": "Kothapalle"
  },
  {
    "code": 5140,
    "district_code": 517,
    "name": "Kotha Patnam"
  },
  {
    "code": 4927,
    "district_code": 747,
    "name": "Kothapeta"
  },
  {
    "code": 4834,
    "district_code": 521,
    "name": "Kothavalasa"
  },
  {
    "code": 4772,
    "district_code": 519,
    "name": "Kothuru"
  },
  {
    "code": 5178,
    "district_code": 515,
    "name": "Kovur"
  },
  {
    "code": 4958,
    "district_code": 505,
    "name": "Kovvur"
  },
  {
    "code": 5252,
    "district_code": 511,
    "name": "Kowthalam"
  },
  {
    "code": 4952,
    "district_code": 748,
    "name": "Koyyalagudem"
  },
  {
    "code": 4851,
    "district_code": 745,
    "name": "Koyyuru"
  },
  {
    "code": 5277,
    "district_code": 511,
    "name": "Krishnagiri"
  },
  {
    "code": 5051,
    "district_code": 751,
    "name": "Krosuru"
  },
  {
    "code": 5018,
    "district_code": 510,
    "name": "Kruthivennu"
  },
  {
    "code": 5323,
    "district_code": 502,
    "name": "Kudair"
  },
  {
    "code": 4735,
    "district_code": 748,
    "name": "Kukunoor"
  },
  {
    "code": 5382,
    "district_code": 752,
    "name": "Kumara Venkata Bhupala Puram"
  },
  {
    "code": 4731,
    "district_code": 745,
    "name": "Kunavaram"
  },
  {
    "code": 5333,
    "district_code": 502,
    "name": "Kundurpi"
  },
  {
    "code": 5427,
    "district_code": 503,
    "name": "Kuppam"
  },
  {
    "code": 5389,
    "district_code": 753,
    "name": "Kurabalakota"
  },
  {
    "code": 5103,
    "district_code": 517,
    "name": "Kurichedu"
  },
  {
    "code": 5259,
    "district_code": 511,
    "name": "Kurnool Rural"
  },
  {
    "code": 7183,
    "district_code": 511,
    "name": "Kurnool Urban"
  },
  {
    "code": 4809,
    "district_code": 743,
    "name": "Kurupam"
  },
  {
    "code": 4833,
    "district_code": 521,
    "name": "Lakkavarapukota"
  },
  {
    "code": 5240,
    "district_code": 753,
    "name": "Lakkireddipalli"
  },
  {
    "code": 4804,
    "district_code": 519,
    "name": "Laveru"
  },
  {
    "code": 4787,
    "district_code": 519,
    "name": "Laxminarasupeta"
  },
  {
    "code": 5365,
    "district_code": 754,
    "name": "Lepakshi"
  },
  {
    "code": 5218,
    "district_code": 504,
    "name": "Lingala"
  },
  {
    "code": 4945,
    "district_code": 748,
    "name": "Lingapalem"
  },
  {
    "code": 5150,
    "district_code": 515,
    "name": "Lingasamudram"
  },
  {
    "code": 5048,
    "district_code": 751,
    "name": "Machavaram"
  },
  {
    "code": 5040,
    "district_code": 751,
    "name": "Macherla"
  },
  {
    "code": 7429,
    "district_code": 510,
    "name": "Machilipatnam North"
  },
  {
    "code": 5034,
    "district_code": 510,
    "name": "Machilipatnam South"
  },
  {
    "code": 5350,
    "district_code": 754,
    "name": "Madakasira"
  },
  {
    "code": 5392,
    "district_code": 753,
    "name": "Madanapalle"
  },
  {
    "code": 5292,
    "district_code": 511,
    "name": "Maddikera (East)"
  },
  {
    "code": 5127,
    "district_code": 517,
    "name": "Maddipadu"
  },
  {
    "code": 4857,
    "district_code": 744,
    "name": "Madugula"
  },
  {
    "code": 5285,
    "district_code": 755,
    "name": "Mahanandi"
  },
  {
    "code": 6837,
    "district_code": 520,
    "name": "Maharanipeta"
  },
  {
    "code": 4875,
    "district_code": 744,
    "name": "Makavarapalem"
  },
  {
    "code": 4813,
    "district_code": 743,
    "name": "Makkuva"
  },
  {
    "code": 4938,
    "district_code": 747,
    "name": "Malikipuram"
  },
  {
    "code": 4936,
    "district_code": 747,
    "name": "Mamidikuduru"
  },
  {
    "code": 4920,
    "district_code": 747,
    "name": "Mandapeta"
  },
  {
    "code": 4776,
    "district_code": 519,
    "name": "Mandasa"
  },
  {
    "code": 5015,
    "district_code": 748,
    "name": "Mandavalli"
  },
  {
    "code": 5055,
    "district_code": 506,
    "name": "Mangalagiri"
  },
  {
    "code": 5250,
    "district_code": 511,
    "name": "Mantralayam"
  },
  {
    "code": 5183,
    "district_code": 515,
    "name": "Manubolu"
  },
  {
    "code": 4884,
    "district_code": 745,
    "name": "Maredumilli"
  },
  {
    "code": 5115,
    "district_code": 517,
    "name": "Markapuram"
  },
  {
    "code": 5163,
    "district_code": 515,
    "name": "Marripadu"
  },
  {
    "code": 5129,
    "district_code": 517,
    "name": "Marripudi"
  },
  {
    "code": 5106,
    "district_code": 750,
    "name": "Martur"
  },
  {
    "code": 5073,
    "district_code": 506,
    "name": "Medikonduru"
  },
  {
    "code": 4774,
    "district_code": 519,
    "name": "Meliaputti"
  },
  {
    "code": 4824,
    "district_code": 521,
    "name": "Mentada"
  },
  {
    "code": 4822,
    "district_code": 521,
    "name": "Merakamudidam"
  },
  {
    "code": 5267,
    "district_code": 755,
    "name": "Midthur"
  },
  {
    "code": 4986,
    "district_code": 523,
    "name": "Mogalthur"
  },
  {
    "code": 5036,
    "district_code": 510,
    "name": "Mopidevi"
  },
  {
    "code": 5032,
    "district_code": 510,
    "name": "Movva"
  },
  {
    "code": 5216,
    "district_code": 504,
    "name": "Muddanur"
  },
  {
    "code": 5339,
    "district_code": 754,
    "name": "Mudigubba"
  },
  {
    "code": 5020,
    "district_code": 748,
    "name": "Mudinepalle"
  },
  {
    "code": 6839,
    "district_code": 520,
    "name": "Mulagada"
  },
  {
    "code": 5367,
    "district_code": 753,
    "name": "Mulakalacheruvu"
  },
  {
    "code": 4932,
    "district_code": 747,
    "name": "Mummidivaram"
  },
  {
    "code": 4877,
    "district_code": 744,
    "name": "Munagapaka"
  },
  {
    "code": 4841,
    "district_code": 745,
    "name": "Munchingi Puttu"
  },
  {
    "code": 5113,
    "district_code": 517,
    "name": "Mundlamuru"
  },
  {
    "code": 5068,
    "district_code": 751,
    "name": "Muppalla"
  },
  {
    "code": 5002,
    "district_code": 748,
    "name": "Musunuru"
  },
  {
    "code": 5181,
    "district_code": 515,
    "name": "Muthukur"
  },
  {
    "code": 4995,
    "district_code": 749,
    "name": "Mylavaram"
  },
  {
    "code": 5200,
    "district_code": 504,
    "name": "Mylavaram"
  },
  {
    "code": 5069,
    "district_code": 751,
    "name": "Nadendla"
  },
  {
    "code": 5403,
    "district_code": 752,
    "name": "Nagalapuram"
  },
  {
    "code": 5095,
    "district_code": 750,
    "name": "Nagaram"
  },
  {
    "code": 5406,
    "district_code": 503,
    "name": "Nagari"
  },
  {
    "code": 5038,
    "district_code": 510,
    "name": "Nagayalanka"
  },
  {
    "code": 5126,
    "district_code": 517,
    "name": "Naguluppala Padu"
  },
  {
    "code": 5194,
    "district_code": 752,
    "name": "Naidupet"
  },
  {
    "code": 4880,
    "district_code": 744,
    "name": "Nakkapalli"
  },
  {
    "code": 5359,
    "district_code": 754,
    "name": "Nallachervu"
  },
  {
    "code": 4956,
    "district_code": 505,
    "name": "Nallajerla"
  },
  {
    "code": 5344,
    "district_code": 754,
    "name": "Nallamada"
  },
  {
    "code": 5341,
    "district_code": 754,
    "name": "Nambulapulakunta"
  },
  {
    "code": 5243,
    "district_code": 753,
    "name": "Nandalur"
  },
  {
    "code": 5255,
    "district_code": 511,
    "name": "Nandavaram"
  },
  {
    "code": 4782,
    "district_code": 519,
    "name": "Nandigam"
  },
  {
    "code": 4993,
    "district_code": 749,
    "name": "Nandigama"
  },
  {
    "code": 5260,
    "district_code": 755,
    "name": "Nandikotkur"
  },
  {
    "code": 5014,
    "district_code": 510,
    "name": "Nandivada"
  },
  {
    "code": 5284,
    "district_code": 755,
    "name": "Nandyal Rural"
  },
  {
    "code": 7425,
    "district_code": 755,
    "name": "Nandyal Urban"
  },
  {
    "code": 4799,
    "district_code": 519,
    "name": "Narasannapeta"
  },
  {
    "code": 4987,
    "district_code": 523,
    "name": "Narasapuram"
  },
  {
    "code": 5067,
    "district_code": 751,
    "name": "Narasaraopet"
  },
  {
    "code": 5400,
    "district_code": 752,
    "name": "Narayanavanam"
  },
  {
    "code": 5328,
    "district_code": 502,
    "name": "Narpala"
  },
  {
    "code": 4854,
    "district_code": 744,
    "name": "Narsipatnam"
  },
  {
    "code": 4852,
    "district_code": 744,
    "name": "Nathavaram"
  },
  {
    "code": 5060,
    "district_code": 751,
    "name": "Nekarikallu"
  },
  {
    "code": 4837,
    "district_code": 521,
    "name": "Nellimarla"
  },
  {
    "code": 5177,
    "district_code": 515,
    "name": "Nellore Rural"
  },
  {
    "code": 7182,
    "district_code": 515,
    "name": "Nellore Urban"
  },
  {
    "code": 4960,
    "district_code": 505,
    "name": "Nidadavole"
  },
  {
    "code": 4968,
    "district_code": 748,
    "name": "Nidamarru"
  },
  {
    "code": 5393,
    "district_code": 753,
    "name": "Nimmanapalle"
  },
  {
    "code": 5404,
    "district_code": 503,
    "name": "Nindra"
  },
  {
    "code": 5094,
    "district_code": 750,
    "name": "Nizampatnam"
  },
  {
    "code": 5063,
    "district_code": 751,
    "name": "Nuzendla"
  },
  {
    "code": 5003,
    "district_code": 748,
    "name": "Nuzividu"
  },
  {
    "code": 5358,
    "district_code": 754,
    "name": "Obuladevaracheruvu"
  },
  {
    "code": 5248,
    "district_code": 753,
    "name": "Obulavaripalle"
  },
  {
    "code": 5139,
    "district_code": 517,
    "name": "Ongole Rural"
  },
  {
    "code": 7430,
    "district_code": 517,
    "name": "Ongole Urban"
  },
  {
    "code": 5268,
    "district_code": 511,
    "name": "Orvakal"
  },
  {
    "code": 5295,
    "district_code": 755,
    "name": "Owk"
  },
  {
    "code": 5189,
    "district_code": 752,
    "name": "Ozili"
  },
  {
    "code": 4818,
    "district_code": 743,
    "name": "Pachipenta"
  },
  {
    "code": 4847,
    "district_code": 745,
    "name": "Paderu"
  },
  {
    "code": 4864,
    "district_code": 520,
    "name": "Padmanabham"
  },
  {
    "code": 5261,
    "district_code": 755,
    "name": "Pagidyala"
  },
  {
    "code": 5396,
    "district_code": 752,
    "name": "Pakala"
  },
  {
    "code": 4977,
    "district_code": 523,
    "name": "Palacoderu"
  },
  {
    "code": 4988,
    "district_code": 523,
    "name": "Palacole"
  },
  {
    "code": 4784,
    "district_code": 743,
    "name": "Palakonda"
  },
  {
    "code": 5422,
    "district_code": 503,
    "name": "Palamaner"
  },
  {
    "code": 4775,
    "district_code": 519,
    "name": "Palasa"
  },
  {
    "code": 5432,
    "district_code": 503,
    "name": "Palasamudram"
  },
  {
    "code": 5028,
    "district_code": 510,
    "name": "Pamarru"
  },
  {
    "code": 5315,
    "district_code": 502,
    "name": "Pamidi"
  },
  {
    "code": 5026,
    "district_code": 510,
    "name": "Pamidimukkala"
  },
  {
    "code": 5266,
    "district_code": 755,
    "name": "Pamulapadu"
  },
  {
    "code": 5146,
    "district_code": 517,
    "name": "Pamur"
  },
  {
    "code": 5280,
    "district_code": 755,
    "name": "Panyam"
  },
  {
    "code": 4870,
    "district_code": 744,
    "name": "Paravada"
  },
  {
    "code": 5108,
    "district_code": 750,
    "name": "Parchur"
  },
  {
    "code": 5355,
    "district_code": 754,
    "name": "Parigi"
  },
  {
    "code": 4812,
    "district_code": 743,
    "name": "Parvathipuram"
  },
  {
    "code": 4773,
    "district_code": 519,
    "name": "Pathapatnam"
  },
  {
    "code": 5290,
    "district_code": 511,
    "name": "Pattikonda"
  },
  {
    "code": 4881,
    "district_code": 744,
    "name": "Payakaraopeta"
  },
  {
    "code": 5294,
    "district_code": 755,
    "name": "Peapully"
  },
  {
    "code": 4842,
    "district_code": 745,
    "name": "Peda Bayalu"
  },
  {
    "code": 5144,
    "district_code": 517,
    "name": "Pedacherlo Palle"
  },
  {
    "code": 4868,
    "district_code": 520,
    "name": "Pedagantyada"
  },
  {
    "code": 5075,
    "district_code": 506,
    "name": "Pedakakani"
  },
  {
    "code": 5057,
    "district_code": 751,
    "name": "Pedakurapadu"
  },
  {
    "code": 5030,
    "district_code": 510,
    "name": "Pedana"
  },
  {
    "code": 5082,
    "district_code": 506,
    "name": "Pedanandipadu"
  },
  {
    "code": 4965,
    "district_code": 748,
    "name": "Pedapadu"
  },
  {
    "code": 5022,
    "district_code": 510,
    "name": "Pedaparupudi"
  },
  {
    "code": 4915,
    "district_code": 746,
    "name": "Pedapudi"
  },
  {
    "code": 4964,
    "district_code": 748,
    "name": "Pedavegi"
  },
  {
    "code": 5101,
    "district_code": 517,
    "name": "Peddaaraveedu"
  },
  {
    "code": 5253,
    "district_code": 511,
    "name": "Pedda Kadubur"
  },
  {
    "code": 5369,
    "district_code": 753,
    "name": "Peddamandyam"
  },
  {
    "code": 5201,
    "district_code": 504,
    "name": "Peddamudiam"
  },
  {
    "code": 5416,
    "district_code": 503,
    "name": "Peddapanjani"
  },
  {
    "code": 5314,
    "district_code": 502,
    "name": "Peddapappur"
  },
  {
    "code": 4903,
    "district_code": 746,
    "name": "Peddapuram"
  },
  {
    "code": 5390,
    "district_code": 753,
    "name": "Pedda Thippasamudram"
  },
  {
    "code": 5311,
    "district_code": 502,
    "name": "Peddavaduguru"
  },
  {
    "code": 5195,
    "district_code": 752,
    "name": "Pellakur"
  },
  {
    "code": 5244,
    "district_code": 753,
    "name": "Penagalur"
  },
  {
    "code": 5024,
    "district_code": 510,
    "name": "Penamaluru"
  },
  {
    "code": 5232,
    "district_code": 504,
    "name": "Pendlimarry"
  },
  {
    "code": 4862,
    "district_code": 520,
    "name": "Pendurthi"
  },
  {
    "code": 4969,
    "district_code": 523,
    "name": "Pentapadu"
  },
  {
    "code": 4992,
    "district_code": 749,
    "name": "Penuganchiprolu"
  },
  {
    "code": 4980,
    "district_code": 523,
    "name": "Penugonda"
  },
  {
    "code": 5356,
    "district_code": 754,
    "name": "Penukonda"
  },
  {
    "code": 4978,
    "district_code": 523,
    "name": "Penumantra"
  },
  {
    "code": 5409,
    "district_code": 503,
    "name": "Penumur"
  },
  {
    "code": 4971,
    "district_code": 505,
    "name": "Peravali"
  },
  {
    "code": 4934,
    "district_code": 747,
    "name": "P.Gannavaram"
  },
  {
    "code": 5072,
    "district_code": 506,
    "name": "Phirangipuram"
  },
  {
    "code": 5401,
    "district_code": 752,
    "name": "Pichatur"
  },
  {
    "code": 5047,
    "district_code": 751,
    "name": "Piduguralla"
  },
  {
    "code": 5386,
    "district_code": 753,
    "name": "Pileru"
  },
  {
    "code": 4911,
    "district_code": 746,
    "name": "Pithapuram"
  },
  {
    "code": 5091,
    "district_code": 750,
    "name": "Pittalavanipalem"
  },
  {
    "code": 5176,
    "district_code": 515,
    "name": "Podalakur"
  },
  {
    "code": 5120,
    "district_code": 517,
    "name": "Podili"
  },
  {
    "code": 4982,
    "district_code": 523,
    "name": "Poduru"
  },
  {
    "code": 4800,
    "district_code": 519,
    "name": "Polaki"
  },
  {
    "code": 4949,
    "district_code": 748,
    "name": "Polavaram"
  },
  {
    "code": 4803,
    "district_code": 519,
    "name": "Ponduru"
  },
  {
    "code": 5143,
    "district_code": 517,
    "name": "Ponnaluru"
  },
  {
    "code": 5084,
    "district_code": 506,
    "name": "Ponnur"
  },
  {
    "code": 4838,
    "district_code": 521,
    "name": "Poosapatirega"
  },
  {
    "code": 5208,
    "district_code": 504,
    "name": "Porumamilla"
  },
  {
    "code": 5081,
    "district_code": 506,
    "name": "Prathipadu"
  },
  {
    "code": 4900,
    "district_code": 746,
    "name": "Prathipadu"
  },
  {
    "code": 5214,
    "district_code": 504,
    "name": "Proddutur"
  },
  {
    "code": 5395,
    "district_code": 503,
    "name": "Pulicherla"
  },
  {
    "code": 5219,
    "district_code": 504,
    "name": "Pulivendula"
  },
  {
    "code": 5098,
    "district_code": 517,
    "name": "Pullalacheruvu"
  },
  {
    "code": 5247,
    "district_code": 753,
    "name": "Pullampeta"
  },
  {
    "code": 5415,
    "district_code": 503,
    "name": "Punganuru"
  },
  {
    "code": 5410,
    "district_code": 503,
    "name": "Puthalapattu"
  },
  {
    "code": 5326,
    "district_code": 502,
    "name": "Putlur"
  },
  {
    "code": 5357,
    "district_code": 754,
    "name": "Puttaparthy"
  },
  {
    "code": 5407,
    "district_code": 752,
    "name": "Puttur"
  },
  {
    "code": 5132,
    "district_code": 517,
    "name": "Racherla"
  },
  {
    "code": 4796,
    "district_code": 521,
    "name": "Rajam"
  },
  {
    "code": 4907,
    "district_code": 505,
    "name": "Rajamahendravaram Rural"
  },
  {
    "code": 4906,
    "district_code": 505,
    "name": "Rajamahendravaram Urban"
  },
  {
    "code": 5246,
    "district_code": 753,
    "name": "Rajampet"
  },
  {
    "code": 4908,
    "district_code": 505,
    "name": "Rajanagaram"
  },
  {
    "code": 4888,
    "district_code": 745,
    "name": "Rajavommangi"
  },
  {
    "code": 5202,
    "district_code": 504,
    "name": "Rajupalem"
  },
  {
    "code": 5059,
    "district_code": 751,
    "name": "Rajupalem"
  },
  {
    "code": 4819,
    "district_code": 521,
    "name": "Ramabhadrapuram"
  },
  {
    "code": 5398,
    "district_code": 752,
    "name": "Ramachandrapuram"
  },
  {
    "code": 4924,
    "district_code": 747,
    "name": "Ramachandrapuram"
  },
  {
    "code": 5348,
    "district_code": 754,
    "name": "Ramagiri"
  },
  {
    "code": 5428,
    "district_code": 503,
    "name": "Ramakuppam"
  },
  {
    "code": 5241,
    "district_code": 753,
    "name": "Ramapuram"
  },
  {
    "code": 5414,
    "district_code": 753,
    "name": "Ramasamudram"
  },
  {
    "code": 4883,
    "district_code": 744,
    "name": "Rambilli"
  },
  {
    "code": 4895,
    "district_code": 745,
    "name": "Rampachodavaram"
  },
  {
    "code": 4805,
    "district_code": 519,
    "name": "Ranastalam"
  },
  {
    "code": 4909,
    "district_code": 505,
    "name": "Rangampeta"
  },
  {
    "code": 5331,
    "district_code": 502,
    "name": "Rapthadu"
  },
  {
    "code": 5175,
    "district_code": 515,
    "name": "Rapur"
  },
  {
    "code": 4856,
    "district_code": 744,
    "name": "Ravikamatham"
  },
  {
    "code": 4926,
    "district_code": 747,
    "name": "Ravulapalem"
  },
  {
    "code": 5239,
    "district_code": 753,
    "name": "Rayachoti"
  },
  {
    "code": 5305,
    "district_code": 502,
    "name": "Rayadurg"
  },
  {
    "code": 4921,
    "district_code": 747,
    "name": "Rayavaram"
  },
  {
    "code": 4937,
    "district_code": 747,
    "name": "Razole"
  },
  {
    "code": 4999,
    "district_code": 749,
    "name": "Reddigudem"
  },
  {
    "code": 4786,
    "district_code": 521,
    "name": "Regidi Amadalavalasa"
  },
  {
    "code": 5376,
    "district_code": 752,
    "name": "Renigunta"
  },
  {
    "code": 5043,
    "district_code": 751,
    "name": "Rentachintala"
  },
  {
    "code": 5096,
    "district_code": 750,
    "name": "Repalle"
  },
  {
    "code": 5349,
    "district_code": 754,
    "name": "Roddam"
  },
  {
    "code": 5353,
    "district_code": 754,
    "name": "Rolla"
  },
  {
    "code": 4855,
    "district_code": 744,
    "name": "Rolugunta"
  },
  {
    "code": 5066,
    "district_code": 751,
    "name": "Rompicharla"
  },
  {
    "code": 5373,
    "district_code": 503,
    "name": "Rompicherla"
  },
  {
    "code": 4891,
    "district_code": 746,
    "name": "Rowthulapudi"
  },
  {
    "code": 5297,
    "district_code": 755,
    "name": "Rudravaram"
  },
  {
    "code": 4861,
    "district_code": 744,
    "name": "Sabbavaram"
  },
  {
    "code": 4939,
    "district_code": 747,
    "name": "Sakhinetipalli"
  },
  {
    "code": 4817,
    "district_code": 743,
    "name": "Salur"
  },
  {
    "code": 4910,
    "district_code": 746,
    "name": "Samalkota"
  },
  {
    "code": 5237,
    "district_code": 753,
    "name": "Sambepalle"
  },
  {
    "code": 5171,
    "district_code": 515,
    "name": "Sangam"
  },
  {
    "code": 5300,
    "district_code": 755,
    "name": "Sanjamala"
  },
  {
    "code": 4892,
    "district_code": 746,
    "name": "Sankhavaram"
  },
  {
    "code": 4790,
    "district_code": 519,
    "name": "Santhabommali"
  },
  {
    "code": 4795,
    "district_code": 521,
    "name": "Santhakaviti"
  },
  {
    "code": 5104,
    "district_code": 750,
    "name": "Santhamaguluru"
  },
  {
    "code": 5138,
    "district_code": 517,
    "name": "Santhanuthala Padu"
  },
  {
    "code": 5425,
    "district_code": 503,
    "name": "Santhipuram"
  },
  {
    "code": 4788,
    "district_code": 519,
    "name": "Saravakota"
  },
  {
    "code": 4793,
    "district_code": 519,
    "name": "Sarubujjili"
  },
  {
    "code": 5058,
    "district_code": 751,
    "name": "Sattenapalli"
  },
  {
    "code": 5402,
    "district_code": 752,
    "name": "Satyavedu"
  },
  {
    "code": 5064,
    "district_code": 751,
    "name": "Savalyapuram H/O Kanamarlapudi"
  },
  {
    "code": 6836,
    "district_code": 520,
    "name": "Seethammadhara"
  },
  {
    "code": 4770,
    "district_code": 743,
    "name": "Seethampeta"
  },
  {
    "code": 4814,
    "district_code": 743,
    "name": "Seethanagaram"
  },
  {
    "code": 4896,
    "district_code": 505,
    "name": "Seethanagaram"
  },
  {
    "code": 5153,
    "district_code": 515,
    "name": "Seetharamapuram"
  },
  {
    "code": 5332,
    "district_code": 502,
    "name": "Settur"
  },
  {
    "code": 5229,
    "district_code": 504,
    "name": "Sidhout"
  },
  {
    "code": 5217,
    "district_code": 504,
    "name": "Simhadripuram"
  },
  {
    "code": 5325,
    "district_code": 502,
    "name": "Singanamala"
  },
  {
    "code": 5149,
    "district_code": 517,
    "name": "Singarayakonda"
  },
  {
    "code": 5286,
    "district_code": 755,
    "name": "Sirvel"
  },
  {
    "code": 5204,
    "district_code": 504,
    "name": "S.Mydukur"
  },
  {
    "code": 5394,
    "district_code": 503,
    "name": "Sodam"
  },
  {
    "code": 5412,
    "district_code": 503,
    "name": "Somala"
  },
  {
    "code": 5363,
    "district_code": 754,
    "name": "Somandepalli"
  },
  {
    "code": 4780,
    "district_code": 519,
    "name": "Sompeta"
  },
  {
    "code": 4882,
    "district_code": 744,
    "name": "S.Rayavaram"
  },
  {
    "code": 5206,
    "district_code": 504,
    "name": "Sri Avadhutha Kasinayana"
  },
  {
    "code": 4802,
    "district_code": 519,
    "name": "Srikakulam"
  },
  {
    "code": 5378,
    "district_code": 752,
    "name": "Srikalahasti"
  },
  {
    "code": 5419,
    "district_code": 503,
    "name": "Srirangarajapuram"
  },
  {
    "code": 6538,
    "district_code": 755,
    "name": "Srisailam"
  },
  {
    "code": 4831,
    "district_code": 521,
    "name": "Srungavarapukota"
  },
  {
    "code": 5197,
    "district_code": 752,
    "name": "Sullurpeta"
  },
  {
    "code": 5185,
    "district_code": 515,
    "name": "Sydapuram"
  },
  {
    "code": 5198,
    "district_code": 752,
    "name": "Tada"
  },
  {
    "code": 5054,
    "district_code": 506,
    "name": "Tadepalli"
  },
  {
    "code": 4961,
    "district_code": 523,
    "name": "Tadepalligudem"
  },
  {
    "code": 5056,
    "district_code": 506,
    "name": "Tadikonda"
  },
  {
    "code": 5338,
    "district_code": 754,
    "name": "Tadimarri"
  },
  {
    "code": 5313,
    "district_code": 502,
    "name": "Tadipatri"
  },
  {
    "code": 4950,
    "district_code": 505,
    "name": "Tallapudi"
  },
  {
    "code": 4930,
    "district_code": 746,
    "name": "Tallarevu"
  },
  {
    "code": 5340,
    "district_code": 754,
    "name": "Talupula"
  },
  {
    "code": 5360,
    "district_code": 754,
    "name": "Tanakal"
  },
  {
    "code": 5141,
    "district_code": 517,
    "name": "Tangutur"
  },
  {
    "code": 4972,
    "district_code": 523,
    "name": "Tanuku"
  },
  {
    "code": 5118,
    "district_code": 517,
    "name": "Tarlupadu"
  },
  {
    "code": 4789,
    "district_code": 519,
    "name": "Tekkali"
  },
  {
    "code": 5078,
    "district_code": 506,
    "name": "Tenali"
  },
  {
    "code": 5121,
    "district_code": 517,
    "name": "Thallur"
  },
  {
    "code": 5368,
    "district_code": 753,
    "name": "Thamballapalle"
  },
  {
    "code": 5418,
    "district_code": 503,
    "name": "Thavanampalle"
  },
  {
    "code": 4821,
    "district_code": 521,
    "name": "Therlam"
  },
  {
    "code": 4901,
    "district_code": 746,
    "name": "Thondangi"
  },
  {
    "code": 5221,
    "district_code": 504,
    "name": "Thondur"
  },
  {
    "code": 5180,
    "district_code": 515,
    "name": "Thotapalligudur"
  },
  {
    "code": 5025,
    "district_code": 510,
    "name": "Thotlavalluru"
  },
  {
    "code": 5379,
    "district_code": 752,
    "name": "Thottambedu"
  },
  {
    "code": 5053,
    "district_code": 506,
    "name": "Thulluru"
  },
  {
    "code": 5375,
    "district_code": 752,
    "name": "Tirupati (Rural)"
  },
  {
    "code": 5383,
    "district_code": 752,
    "name": "Tirupati (Urban)"
  },
  {
    "code": 4997,
    "district_code": 749,
    "name": "Tiruvuru"
  },
  {
    "code": 4946,
    "district_code": 748,
    "name": "T.Narasapuram"
  },
  {
    "code": 5099,
    "district_code": 517,
    "name": "Tripuranthakam"
  },
  {
    "code": 5238,
    "district_code": 753,
    "name": "T.Sundupalle"
  },
  {
    "code": 5085,
    "district_code": 750,
    "name": "Tsunduru"
  },
  {
    "code": 5293,
    "district_code": 511,
    "name": "Tuggali"
  },
  {
    "code": 4890,
    "district_code": 746,
    "name": "Tuni"
  },
  {
    "code": 5154,
    "district_code": 515,
    "name": "Udayagiri"
  },
  {
    "code": 4912,
    "district_code": 746,
    "name": "U.Kothapalli"
  },
  {
    "code": 5152,
    "district_code": 515,
    "name": "Ulavapadu"
  },
  {
    "code": 4976,
    "district_code": 523,
    "name": "Undi"
  },
  {
    "code": 4970,
    "district_code": 505,
    "name": "Undrajavaram"
  },
  {
    "code": 5013,
    "district_code": 510,
    "name": "Unguturu"
  },
  {
    "code": 4962,
    "district_code": 748,
    "name": "Unguturu"
  },
  {
    "code": 4942,
    "district_code": 747,
    "name": "Uppalaguptam"
  },
  {
    "code": 5317,
    "district_code": 502,
    "name": "Uravakonda"
  },
  {
    "code": 5302,
    "district_code": 755,
    "name": "Uyyalawada"
  },
  {
    "code": 5399,
    "district_code": 752,
    "name": "Vadamalapet"
  },
  {
    "code": 5316,
    "district_code": 502,
    "name": "Vajrakarur"
  },
  {
    "code": 4781,
    "district_code": 519,
    "name": "Vajrapukotturu"
  },
  {
    "code": 5192,
    "district_code": 752,
    "name": "Vakadu"
  },
  {
    "code": 5225,
    "district_code": 504,
    "name": "Vallur"
  },
  {
    "code": 5388,
    "district_code": 753,
    "name": "Valmikipuram"
  },
  {
    "code": 4785,
    "district_code": 521,
    "name": "Vangara"
  },
  {
    "code": 5381,
    "district_code": 752,
    "name": "Varadaiahpalem"
  },
  {
    "code": 4733,
    "district_code": 745,
    "name": "Vararamachandrapuram"
  },
  {
    "code": 5155,
    "district_code": 515,
    "name": "Varikuntapadu"
  },
  {
    "code": 4990,
    "district_code": 749,
    "name": "Vatsavai"
  },
  {
    "code": 5080,
    "district_code": 506,
    "name": "Vatticherukuru"
  },
  {
    "code": 5397,
    "district_code": 503,
    "name": "Vedurukuppam"
  },
  {
    "code": 5242,
    "district_code": 753,
    "name": "Veeraballe"
  },
  {
    "code": 4769,
    "district_code": 743,
    "name": "Veeraghattam"
  },
  {
    "code": 5222,
    "district_code": 504,
    "name": "Veerapunayunipalle"
  },
  {
    "code": 4983,
    "district_code": 523,
    "name": "Veeravasaram"
  },
  {
    "code": 4994,
    "district_code": 749,
    "name": "Veerullapadu"
  },
  {
    "code": 4734,
    "district_code": 748,
    "name": "Velairpadu"
  },
  {
    "code": 5278,
    "district_code": 511,
    "name": "Veldurthy"
  },
  {
    "code": 5041,
    "district_code": 751,
    "name": "Veldurthy"
  },
  {
    "code": 5135,
    "district_code": 517,
    "name": "Veligandla"
  },
  {
    "code": 5282,
    "district_code": 755,
    "name": "Velugodu"
  },
  {
    "code": 5233,
    "district_code": 504,
    "name": "Vempalli"
  },
  {
    "code": 5220,
    "district_code": 504,
    "name": "Vemula"
  },
  {
    "code": 5087,
    "district_code": 750,
    "name": "Vemuru"
  },
  {
    "code": 5182,
    "district_code": 515,
    "name": "Venkatachalam"
  },
  {
    "code": 5187,
    "district_code": 752,
    "name": "Venkatagiri"
  },
  {
    "code": 5424,
    "district_code": 503,
    "name": "Venkatagirikota"
  },
  {
    "code": 4832,
    "district_code": 521,
    "name": "Vepada"
  },
  {
    "code": 5124,
    "district_code": 750,
    "name": "Vetapalem"
  },
  {
    "code": 5308,
    "district_code": 502,
    "name": "Vidapanakal"
  },
  {
    "code": 5168,
    "district_code": 515,
    "name": "Vidavalur"
  },
  {
    "code": 5405,
    "district_code": 503,
    "name": "Vijayapuram"
  },
  {
    "code": 5010,
    "district_code": 749,
    "name": "Vijayawada Central"
  },
  {
    "code": 6863,
    "district_code": 749,
    "name": "Vijayawada East"
  },
  {
    "code": 6864,
    "district_code": 749,
    "name": "Vijayawada North"
  },
  {
    "code": 5011,
    "district_code": 749,
    "name": "Vijayawada (Rural)"
  },
  {
    "code": 6865,
    "district_code": 749,
    "name": "Vijayawada West"
  },
  {
    "code": 5161,
    "district_code": 515,
    "name": "Vinjamur"
  },
  {
    "code": 5062,
    "district_code": 751,
    "name": "Vinukonda"
  },
  {
    "code": 4866,
    "district_code": 520,
    "name": "Visakhapatnam (Rural)"
  },
  {
    "code": 5000,
    "district_code": 749,
    "name": "Vissannapeta"
  },
  {
    "code": 4836,
    "district_code": 521,
    "name": "Vizianagaram Rural"
  },
  {
    "code": 7431,
    "district_code": 521,
    "name": "Vizianagaram Urban"
  },
  {
    "code": 5147,
    "district_code": 515,
    "name": "Voletivaripalem"
  },
  {
    "code": 5228,
    "district_code": 504,
    "name": "Vontimitta"
  },
  {
    "code": 5027,
    "district_code": 510,
    "name": "Vuyyuru"
  },
  {
    "code": 5430,
    "district_code": 503,
    "name": "Yadamarri"
  },
  {
    "code": 5312,
    "district_code": 502,
    "name": "Yadiki"
  },
  {
    "code": 5107,
    "district_code": 750,
    "name": "Yeddana Pudi"
  },
  {
    "code": 4879,
    "district_code": 744,
    "name": "Yelamanchili"
  },
  {
    "code": 4989,
    "district_code": 523,
    "name": "Yelamanchili"
  },
  {
    "code": 4893,
    "district_code": 746,
    "name": "Yeleswaram"
  },
  {
    "code": 5327,
    "district_code": 502,
    "name": "Yellanur"
  },
  {
    "code": 5254,
    "district_code": 511,
    "name": "Yemmiganur"
  },
  {
    "code": 5377,
    "district_code": 752,
    "name": "Yerpedu"
  },
  {
    "code": 5097,
    "district_code": 517,
    "name": "Yerragondapalem"
  },
  {
    "code": 5223,
    "district_code": 504,
    "name": "Yerraguntla"
  },
  {
    "code": 5374,
    "district_code": 752,
    "name": "Yerravaripalem"
  },
  {
    "code": 6063,
    "district_code": 745,
    "name": "Yetapaka"
  },
  {
    "code": 4886,
    "district_code": 745,
    "name": "Y. Ramavaram"
  },
  {
    "code": 5142,
    "district_code": 517,
    "name": "Zarugumalli"
  }
]